indigen/__init__.py
indigen/main.py
indigen/scripts/__init__.py
indigen/scripts/indigen.py
indigen/state_modules/Andhrapradesh_File.py
indigen/state_modules/Assam_File.py
indigen/state_modules/Bengal_File.py
indigen/state_modules/Bihar_File.py
indigen/state_modules/Chattisgarh_File.py
indigen/state_modules/Delhi_File.py
indigen/state_modules/Female_File.py
indigen/state_modules/Goa_File.py
indigen/state_modules/Gujrat_File.py
indigen/state_modules/Haryana_File.py
indigen/state_modules/Himachal_File.py
indigen/state_modules/JK_File.py
indigen/state_modules/Jharkhand_File.py
indigen/state_modules/Karnataka_File.py
indigen/state_modules/Kerala_File.py
indigen/state_modules/Madhyapradesh_File.py
indigen/state_modules/Maharashtra_File.py
indigen/state_modules/Male_File.py
indigen/state_modules/Orissa_File.py
indigen/state_modules/Parsi_File.py
indigen/state_modules/Punjab_File.py
indigen/state_modules/Rajasthan_File.py
indigen/state_modules/Tamil_File.py
indigen/state_modules/Telengana_File.py
indigen/state_modules/Tribal_File.py
indigen/state_modules/Tripura_File.py
indigen/state_modules/Uttarakhand_File.py
indigen/state_modules/Uttarpradesh_File.py
indigen/state_modules/__init__.py
indigen/utils/__init__.py
indigen/utils/common.py
indigen/utils/state_utils.py
indigen-0.1.3.dist-info/LICENSE
indigen-0.1.3.dist-info/METADATA
indigen-0.1.3.dist-info/WHEEL
indigen-0.1.3.dist-info/entry_points.txt
indigen-0.1.3.dist-info/top_level.txt
indigen-0.1.3.dist-info/RECORD
