Metadata-Version: 2.1
Name: indigen
Version: 0.1.3
Summary: A package for generating synthetic names based on Indian states.
Home-page: https://github.com/ghatesudi/indigen
Author: Sudeep Ghate
Author-email: sudeep1129@gmail.com
License: UNKNOWN
Platform: UNKNOWN
